odoo/addons/mail_layout_force/README.rst
odoo/addons/mail_layout_force/__init__.py
odoo/addons/mail_layout_force/__manifest__.py
odoo/addons/mail_layout_force/data/mail_layout.xml
odoo/addons/mail_layout_force/demo/mail_layout.xml
odoo/addons/mail_layout_force/i18n/de.po
odoo/addons/mail_layout_force/i18n/it.po
odoo/addons/mail_layout_force/i18n/mail_layout_force.pot
odoo/addons/mail_layout_force/models/__init__.py
odoo/addons/mail_layout_force/models/email_layout_mapping.py
odoo/addons/mail_layout_force/models/ir_ui_view.py
odoo/addons/mail_layout_force/models/mail_template.py
odoo/addons/mail_layout_force/models/mail_thread.py
odoo/addons/mail_layout_force/readme/CONFIGURE.rst
odoo/addons/mail_layout_force/readme/CONTRIBUTORS.rst
odoo/addons/mail_layout_force/readme/DESCRIPTION.rst
odoo/addons/mail_layout_force/security/ir.model.access.csv
odoo/addons/mail_layout_force/static/description/icon.png
odoo/addons/mail_layout_force/static/description/index.html
odoo/addons/mail_layout_force/tests/__init__.py
odoo/addons/mail_layout_force/tests/test_mail_layout_force.py
odoo/addons/mail_layout_force/views/ir_ui_views.xml
odoo/addons/mail_layout_force/views/mail_template.xml
odoo/addons/mail_layout_force/wizards/__init__.py
odoo/addons/mail_layout_force/wizards/mail_compose_message.py
odoo_addon_mail_layout_force-16.0.2.0.0.4.dist-info/METADATA
odoo_addon_mail_layout_force-16.0.2.0.0.4.dist-info/WHEEL
odoo_addon_mail_layout_force-16.0.2.0.0.4.dist-info/top_level.txt
odoo_addon_mail_layout_force-16.0.2.0.0.4.dist-info/RECORD
